LICENSE
MANIFEST.in
README.rst
requirements.txt
setup.py
ipc_mngr/__init__.py
ipc_mngr/__meta__.py
ipc_mngr/cmd_parser.py
ipc_mngr/com_mngr.py
ipc_mngr/streamer.py
ipc_mngr.egg-info/PKG-INFO
ipc_mngr.egg-info/SOURCES.txt
ipc_mngr.egg-info/dependency_links.txt
ipc_mngr.egg-info/top_level.txt
tests/bytes_ack_nack/__init__.py
tests/bytes_ack_nack/ack_com_mngr.py
tests/bytes_ack_nack/bytes_com_mngr.py
tests/bytes_ack_nack/main.py