Metadata-Version: 1.1
Name: ipc-mngr
Version: 1.0.1
Summary: Interprocess Communication (IPC) Manager to help create a Command structure for sending and receiving messages between processes.
Home-page: https://github.com/justengel/ipc_mngr
Author: Justin Engel
Author-email: jtengel08@gmail.com
License: Proprietary
Download-URL: https://github.com/justengel/ipc_mngr/archive/v1.0.1.tar.gz
Keywords: Interprocess Communication IPC
Platform: any
Classifier: Programming Language :: Python
Classifier: Programming Language :: Python :: 3
Classifier: Operating System :: OS Independent
